odoo/addons/mrp_repair_order/README.rst
odoo/addons/mrp_repair_order/__init__.py
odoo/addons/mrp_repair_order/__manifest__.py
odoo/addons/mrp_repair_order/i18n/ca_ES.po
odoo/addons/mrp_repair_order/i18n/es.po
odoo/addons/mrp_repair_order/i18n/it.po
odoo/addons/mrp_repair_order/i18n/mrp_repair_order.pot
odoo/addons/mrp_repair_order/i18n/pt_BR.po
odoo/addons/mrp_repair_order/models/__init__.py
odoo/addons/mrp_repair_order/models/mrp.py
odoo/addons/mrp_repair_order/models/repair.py
odoo/addons/mrp_repair_order/readme/CONTRIBUTORS.md
odoo/addons/mrp_repair_order/readme/DESCRIPTION.md
odoo/addons/mrp_repair_order/readme/USAGE.md
odoo/addons/mrp_repair_order/static/description/icon.png
odoo/addons/mrp_repair_order/static/description/icon.svg
odoo/addons/mrp_repair_order/static/description/index.html
odoo/addons/mrp_repair_order/tests/__init__.py
odoo/addons/mrp_repair_order/tests/test_mrp_repair_order.py
odoo/addons/mrp_repair_order/views/mrp_production_views.xml
odoo/addons/mrp_repair_order/views/repair_views.xml
odoo_addon_mrp_repair_order-18.0.1.0.0.3.dist-info/METADATA
odoo_addon_mrp_repair_order-18.0.1.0.0.3.dist-info/WHEEL
odoo_addon_mrp_repair_order-18.0.1.0.0.3.dist-info/top_level.txt
odoo_addon_mrp_repair_order-18.0.1.0.0.3.dist-info/RECORD
